ttkbootstrap/__init__.py
ttkbootstrap/__init__.pyi
ttkbootstrap/__main__.py
ttkbootstrap/colorutils.py
ttkbootstrap/constants.py
ttkbootstrap/icons.py
ttkbootstrap/publisher.py
ttkbootstrap/py.typed
ttkbootstrap/scrolled.py
ttkbootstrap/style.py
ttkbootstrap/tableview.py
ttkbootstrap/toast.py
ttkbootstrap/tooltip.py
ttkbootstrap/utility.py
ttkbootstrap/validation.py
ttkbootstrap/window.py
ttkbootstrap/dialogs/__init__.py
ttkbootstrap/dialogs/base.py
ttkbootstrap/dialogs/colorchooser.py
ttkbootstrap/dialogs/colordropper.py
ttkbootstrap/dialogs/datepicker.py
ttkbootstrap/dialogs/dialogs.py
ttkbootstrap/dialogs/fontdialog.py
ttkbootstrap/dialogs/message.py
ttkbootstrap/dialogs/query.py
ttkbootstrap/localization/README.md
ttkbootstrap/localization/__init__.py
ttkbootstrap/localization/msgcat.py
ttkbootstrap/localization/msgs.py
ttkbootstrap/themes/__init__.py
ttkbootstrap/themes/standard.py
ttkbootstrap/themes/user.py
ttkbootstrap/widgets/__init__.py
ttkbootstrap/widgets/dateentry.py
ttkbootstrap/widgets/floodgauge.py
ttkbootstrap/widgets/labeledscale.py
ttkbootstrap/widgets/meter.py
ttkbootstrap/widgets/scrolled.py
ttkbootstrap/widgets/tableview.py
ttkbootstrap/widgets/toast.py
ttkbootstrap/widgets/tooltip.py
ttkbootstrap-1.20.1.dist-info/licenses/LICENSE
ttkcreator/__init__.py
ttkcreator/__main__.py
ttkbootstrap-1.20.1.dist-info/METADATA
ttkbootstrap-1.20.1.dist-info/WHEEL
ttkbootstrap-1.20.1.dist-info/top_level.txt
ttkbootstrap-1.20.1.dist-info/RECORD
