Metadata-Version: 2.4
Name: ttkbootstrap
Version: 1.20.1
Summary: A supercharged theme extension for tkinter that enables on-demand modern flat style themes inspired by Bootstrap.
Author-email: Israel Dryer <israel.dryer@gmail.com>
License-Expression: MIT AND (Apache-2.0 OR BSD-2-Clause)
Project-URL: Homepage, https://github.com/israel-dryer/ttkbootstrap
Project-URL: Documentation, https://ttkbootstrap.readthedocs.io/en/latest/
Keywords: tkinter,theme,ttk,bootstrap,gui,desktop,python3,ui,widgets,theming,cross-platform,modern,responsive,python-gui
Classifier: Development Status :: 5 - Production/Stable
Classifier: Environment :: Win32 (MS Windows)
Classifier: Environment :: X11 Applications :: GTK
Classifier: Intended Audience :: Developers
Classifier: Programming Language :: Python :: 3
Classifier: Programming Language :: Python :: 3.10
Classifier: Programming Language :: Python :: 3.11
Classifier: Programming Language :: Python :: 3.12
Classifier: Programming Language :: Python :: 3.13
Classifier: Programming Language :: Python :: 3.14
Classifier: Topic :: Software Development :: User Interfaces
Classifier: Operating System :: OS Independent
Requires-Python: >=3.10
License-File: LICENSE
Requires-Dist: pillow<13,>=10
Dynamic: license-file
